pesto_common/__init__.py
pesto_common/config/__init__.py
pesto_common/config/configer.py
pesto_common/log/__init__.py
pesto_common/log/logger_factory.py
pesto_common/pipeline/__init__.py
pesto_common/pipeline/step.py
pesto_common/utils/__init__.py
pesto_common/utils/collection_utils.py
pesto_common/utils/date_utils.py
pesto_common/utils/file_utils.py
pesto_common/utils/hash_utils.py
pesto_common/utils/ip_utils.py
pesto_common/utils/number_utils.py
pesto_common/utils/reflect_utils.py
pesto_common-0.0.6.dist-info/METADATA
pesto_common-0.0.6.dist-info/WHEEL
pesto_common-0.0.6.dist-info/top_level.txt
pesto_common-0.0.6.dist-info/RECORD
