Metadata-Version: 2.1
Name: pesto-common
Version: 0.0.6
Summary: Minimalist python utils
Home-page: https://github.com/Dreampie/pesto
Author: Dreampie
Author-email: Dreampie@outlook.com
License: UNKNOWN
Keywords: minimalist,python,utils,pesto
Platform: all
